Workbook

Sheet 00_README
A1: מודול ג׳ · בקרה תקציבית, תזרים וניתוח דאטה
A2: ד״ר שי צבאן · יום עיון: הפרקטיקה הפיננסית והמיסויית ב-SME
B5: שני כללי ברזל
B6: 1. תאימות מלאה | C6: כל נוסחה כאן מתנהגת זהה באקסל למק ובאקסל לווינדוס. אין Power Query, אין מודל נתונים, אין מאקרו, ואין CHAR שמחזירה תו שונה בין המערכות.
B7: 2. נוסחאות באנגלית | C7: שמות הגיליונות, שמות הטבלאות, כותרות העמודות וכל ערך שמופיע בתוך נוסחה הם באנגלית. כך אפשר להעתיק ולהדביק כל נוסחה בלי שהעברית תשבור אותה.
C8: העברית נשארת איפה שהיא צריכה להיות: בנתונים עצמם, בעמודות התצוגה ובכותרות שעל המסך.
B10: החברה שבתרגיל | C10: טכנופיד בע״מ, יבואן ומפיץ ציוד היקפי למשרדים. מחזור שנתי כ-13.5 מיליון ש״ח, תשעה עובדים, בעל שליטה יחיד.
C11: יש לה מלאי (ולכן מחזור מזומן אמיתי), רכב חברה, יתרת בעלים פתוחה, ושלוש מחלקות.
C12: כל הנתונים מלאכותיים ונבנו לתרגול בלבד. אין באמור ייעוץ מס או ייעוץ פיננסי.
B14: מקרא הצבעים | C14: צהוב: כאן מקלידים נוסחה. אפור: נתון קיים, לא נוגעים. קרם: קלט שאתם משנים. לבן: תוצאה שמתמלאת לבד.
B16: בדיקת גרסה | C16: הקלידו בתא ריק =LET(x,1,x) ולחצו Enter. אם התקבל 1, הכול יעבוד.
C17: אם התקבל #NAME? אתם על אקסל 2019 או ישן יותר, ושתי נוסחאות במעבדה 1 לא יעבדו אצלכם. כל שאר המעבדות יעבדו במלואן.
B19: נבנה בכיתה
B20: 04_ETL | C20: מעבדה 1: ניקוי פלט בנק בנוסחאות. תאריך, סכום, תיאור, סיווג, זיהוי כפילויות.
B21: 10_CONTROL | C21: מעבדה 2: לוח בקרת ביצוע מול תקציב, עם התראה על חריגה מעל 10%.
B22: 11_PVM | C22: מעבדה 3: פירוק הסטייה בהכנסות לשלושה גורמים: מחיר, כמות ותמהיל.
B23: 20_WORKCAP | C23: מעבדה 4: ימי גבייה, ימי ספקים, ימי מלאי ומחזור המזומן.
B24: 30_CASH13 | C24: מעבדה 5: תזרים מזומנים ל-13 שבועות עם דירוג ודאות ותרחישים.
B25: 40_ROLLING | C25: מעבדה 6: תחזית מתגלגלת מול קו בסיס נעול.
B27: מגיע מוכן, לשימוש עתידי
B28: 50_CREDIT_TERMS | C28: כמה עולה לתת ללקוח תנאי תשלום ארוכים, ואיזו הנחה שווה לתת תמורת תשלום מיידי.
B29: 60_CASH13_BLANK | C29: אותו מנוע של מעבדה 5, בלי נתונים, מוכן להזנת לקוח אמיתי.
B31: נתונים ועזר
B32: 01_BANK_RAW | C32: פלט בנק גולמי ומלוכלך. חומר הגלם של מעבדה 1.
B33: 02_GL | C33: תנועות הנהלת חשבונות לשנת 2026, הביצוע בפועל.
B34: 03_MAP | C34: טבלת התרגום: מילת מפתח בתיאור הבנק אל קוד סעיף.
B35: 05_BUDGET | C35: התקציב המאושר לשנת 2026.
B36: 99_KEY | C36: כל הנוסחאות, מוכנות להעתקה.
B38: מקרא
C39: להקליד נוסחה
C40: נתון קיים
C41: קלט שאתם משנים
C42: תוצאה אוטומטית

Sheet 01_BANK_RAW
A1: Bank Export (raw) · ינואר עד יוני 2026
A2: בדיוק כפי שיורד מאתר הבנק: שני פורמטים של תאריך, סכומים כטקסט, רווחים כפולים וכפילויות. אל תתקנו ידנית.
A4: RawDate | B4: RawDesc | C4: RawAmount | D4: Ref
A5: 10.4.26 | B5: STATIONERY OFFICE DEPOT | C5: (63,730) | D5: A780067
A6: 26/04/2026 | B6: MUNICIPAL TAX PETAH TIKVA | C6: (53,626) | D6: A780071
A7: 24.5.26 | B7: PAYROLL MONTHLY TRANSFER | C7: (150,118) | D7: A780077
A8: 19.1.26 | B8: CUSTOMER OFFICE PLUS CHAIN | C8: 88,204 | D8: A780014
A9: 10/05/2026 | B9: RECEIPT FROM CUSTOMER ALPHA SYSTEMS | C9: 212,720 | D9: A780079
A10: 18/03/2026 | B10: PAYROLL MONTHLY TRANSFER | C10: (130,039) | D10: A780046
A11: 14/02/2026 | B11: GOOGLE ADS CAMPAIGN | C11: (8,190) | D11: A780032
A12: 28/04/2026 | B12: COFFEE AND KITCHEN SUPPLIES | C12: (23,498) | D12: A780061
A13: 14.5.26 | B13: CUSTOMER MEGATECH LTD | C13: 62,123 | D13: A780076
A14: 04/06/2026 | B14: ELECTRIC UTILITY | C14: (59,804) | D14: A780104
A15: 01/05/2026 | B15: ELECTRIC UTILITY | C15: (86,696) | D15: A780080
... A105: 17.6.26 | B105: LEASE COMPANY CAR | C105: (67,399) | D105: A780095

Sheet 02_GL
A1: General Ledger · ביצוע בפועל 2026
A2: נתון קיים. כותרות העמודות באנגלית כדי שהנוסחאות יהיו נקיות. עמודות ה-Name נועדו לקריאה בלבד.
A4: Date | B4: TxnID | C4: Month | D4: Dept | E4: DeptName | F4: Grp | G4: GrpName | H4: Acct | I4: AcctName | J4: Amount
A5: 46045 | B5: J41001 | C5: 1 | D5: SALES | E5: Direct Sales | F5: REVENUE | G5: Revenue | H5: REVENUE_PROD | I5: Product Revenue | J5: 506397
A6: 46046 | B6: J41002 | C6: 1 | D6: CHANNEL | E6: Distributor Channel | F6: REVENUE | G6: Revenue | H6: REVENUE_PROD | I6: Product Revenue | J6: 257099
A7: 46033 | B7: J41003 | C7: 1 | D7: SERVICE | E7: Service and Support | F7: REVENUE | G7: Revenue | H7: REVENUE_PROD | I7: Product Revenue | J7: 137672
A8: 46029 | B8: J41004 | C8: 1 | D8: SALES | E8: Direct Sales | F8: REVENUE | G8: Revenue | H8: REVENUE_SVC | I8: Service Revenue | J8: 4448
A9: 46032 | B9: J41005 | C9: 1 | D9: CHANNEL | E9: Distributor Channel | F9: REVENUE | G9: Revenue | H9: REVENUE_SVC | I9: Service Revenue | J9: 3880
A10: 46028 | B10: J41006 | C10: 1 | D10: SERVICE | E10: Service and Support | F10: REVENUE | G10: Revenue | H10: REVENUE_SVC | I10: Service Revenue | J10: 78709
A11: 46038 | B11: J41007 | C11: 1 | D11: SALES | E11: Direct Sales | F11: COGS | G11: Cost of Sales | H11: COGS | I11: Cost of Goods Sold | J11: 360359
A12: 46034 | B12: J41008 | C12: 1 | D12: CHANNEL | E12: Distributor Channel | F12: COGS | G12: Cost of Sales | H12: COGS | I12: Cost of Goods Sold | J12: 177899
A13: 46035 | B13: J41009 | C13: 1 | D13: SERVICE | E13: Service and Support | F13: COGS | G13: Cost of Sales | H13: COGS | I13: Cost of Goods Sold | J13: 96319
A14: 46032 | B14: J41010 | C14: 1 | D14: SALES | E14: Direct Sales | F14: OPEX | G14: Operating Expenses | H14: SALARY | I14: Payroll | J14: 76455
A15: 46048 | B15: J41011 | C15: 1 | D15: CHANNEL | E15: Distributor Channel | F15: OPEX | G15: Operating Expenses | H15: SALARY | I15: Payroll | J15: 45861
A16: 46037 | B16: J41012 | C16: 1 | D16: SERVICE | E16: Service and Support | F16: OPEX | G16: Operating Expenses | H16: SALARY | I16: Payroll | J16: 23197
... A472: 46374 | B472: J41468 | C472: 12 | D472: SERVICE | E472: Service and Support | F472: OPEX | G472: Operating Expenses | H472: FINANCE | I472: Finance Costs | J472: 3315

Sheet 03_MAP
A1: Mapping Key · מילת מפתח אל קוד סעיף
A2: הסדר קובע. הנוסחה עוצרת במילה הראשונה שנמצאה, ולכן מילה ספציפית חייבת להופיע מעל מילה כללית.
A4: Keyword | B4: Acct | C4: AcctName | D4: Grp | E4: Note
A5: PROF FEE | B5: PROFSVC | C5: Professional Fees | D5: OPEX | E5: חייב להופיע לפני PAYROLL. אחרת שכר טרחה יסווג כמשכורת.
A6: AUDITOR | B6: PROFSVC | C6: Professional Fees | D6: OPEX | E6: מילה ספציפית לפני מילה כללית. הכלל החשוב ביותר בטבלת מיפוי.
A7: LAW OFFICE | B7: PROFSVC | C7: Professional Fees | D7: OPEX
A8: PAYROLL | B8: SALARY | C8: Payroll | D8: OPEX
A9: SALARY | B9: SALARY | C9: Payroll | D9: OPEX
A10: SOCIAL SEC | B10: SALARY | C10: Payroll | D10: OPEX
A11: PENSION | B11: SALARY | C11: Payroll | D11: OPEX
A12: RENT | B12: RENT | C12: Rent and Facilities | D12: OPEX
A13: MUNICIPAL | B13: RENT | C13: Rent and Facilities | D13: OPEX
A14: ELECTRIC | B14: RENT | C14: Rent and Facilities | D14: OPEX
A15: FUEL | B15: VEHICLE | C15: Vehicle | D15: OPEX
A16: LEASE | B16: VEHICLE | C16: Vehicle | D16: OPEX
A17: GARAGE | B17: VEHICLE | C17: Vehicle | D17: OPEX
A18: TOLL ROAD | B18: VEHICLE | C18: Vehicle | D18: OPEX | E18: נכנס לסל הרכב לצורך כלל 45% בהתאמה למס.
A19: GOOGLE | B19: MARKETING | C19: Marketing | D19: OPEX
A20: FACEBOOK | B20: MARKETING | C20: Marketing | D20: OPEX
A21: CAMPAIGN | B21: MARKETING | C21: Marketing | D21: OPEX
A22: COFFEE | B22: ENTERTAIN | C22: Entertainment | D22: OPEX | E22: כיבוד במקום העסק, 80% בלבד מוכרים.
A23: RESTAURANT | B23: ENTERTAIN | C23: Entertainment | D23: OPEX | E23: אירוח. בדקו סיווג לפני שמכירים.
A24: STATIONERY | B24: OFFICE | C24: Office | D24: OPEX
A25: POSTAL | B25: OFFICE | C25: Office | D25: OPEX
A26: CLEARING | B26: MERCHANT | C26: Merchant Fees | D26: OPEX
A27: CARD FEES | B27: MERCHANT | C27: Merchant Fees | D27: OPEX
A28: INTEREST | B28: FINANCE | C28: Finance Costs | D28: OPEX
A29: BANK FEE | B29: FINANCE | C29: Finance Costs | D29: OPEX
A30: SUPPLIER | B30: COGS | C30: Cost of Goods Sold | D30: COGS
A31: IMPORT | B31: COGS | C31: Cost of Goods Sold | D31: COGS
A32: CUSTOMS | B32: COGS | C32: Cost of Goods Sold | D32: COGS
A33: FREIGHT | B33: COGS | C33: Cost of Goods Sold | D33: COGS
A34: CUSTOMER | B34: REVENUE_PROD | C34: Product Revenue | D34: REVENUE
A35: RECEIPT FROM | B35: REVENUE_PROD | C35: Product Revenue | D35: REVENUE
A36: VAT | B36: TAX | C36: Tax Payments | D36: TAX | E36: תנועת מס ולא הוצאה תפעולית. נכנסת לתזרים ולא לרווח והפסד.
A37: TAX ADVANCE | B37: TAX | C37: Tax Payments | D37: TAX
A38: WITHHOLDING | B38: TAX | C38: Tax Payments | D38: TAX
A39: OWNER DRAW | B39: OWNER | C39: Owner Drawings | D39: OWNER | E39: לא הוצאה. דגל אדום לסעיף 3(ט1).

Sheet 04_ETL
A1: Lab 1 · ניקוי דאטה בנוסחאות
A2: E שליפה, T ניקוי והמרה, L טעינה לטבלה אחידה. הכול עובד זהה במק ובווינדוס.
A3: הלוגיקה: הבנק לא יודע חשבונאות. הוא נותן טקסט חופשי, ואנחנו הופכים אותו לשורה מסווגת שאפשר להשוות לתקציב.
A4: שימו לב לפונקציה UNICHAR ולא CHAR. הפונקציה CHAR מחזירה תו שונה במק ובווינדוס, ולכן ניקוי שמסתמך עליה יעבוד אצל חלק מהכיתה בלבד.
A5: כל הערכים שמופיעים בתוך הנוסחאות כאן הם באנגלית, כדי שאפשר יהיה להעתיק ולהדביק אותן בלי שהעברית תשבור אותן.
A7: RawDate | B7: RawDesc | C7: RawAmount | D7: Ref | E7: 1. CleanDate | F7: 2. Amount | G7: 3. CleanDesc | H7: 4. Acct | I7: 5. DupFlag
A8: ='01_BANK_RAW'!A5 | B8: ='01_BANK_RAW'!B5 | C8: ='01_BANK_RAW'!C5 | D8: ='01_BANK_RAW'!D5 | E8: =_xlfn.LET(t,SUBSTITUTE(TRIM(A8),".","/"),d,VALUE(LEFT(t,FIND("/",t)-1)),r,MID(t,FIND("/",t)+1,20),m,VALUE(LEFT(r,FIND("/",r)-1)),y,VALUE(MID(r,FIND("/",r)+1,4)),DATE(IF(y<100,2000+y,y),m,d)) | F8: =_xlfn.LET(t,SUBSTITUTE(C8,_xlfn.UNICHAR(160)," "),n,SUBSTITUTE(SUBSTITUTE(TRIM(t)," ",""),",",""),IF(LEFT(n,1)="(",-VALUE(SUBSTITUTE(SUBSTITUTE(n,"(",""),")","")),VALUE(n))) | G8: =TRIM(SUBSTITUTE(SUBSTITUTE(SUBSTITUTE(B8,_xlfn.UNICHAR(160)," "),_xlfn.UNICHAR(8207),""),_xlfn.UNICHAR(8206),"")) | H8: =IFERROR(INDEX(MAP[Acct],SUMPRODUCT(MATCH(1,--ISNUMBER(SEARCH(MAP[Keyword],G8)),0))),"UNMAPPED") | I8: =IF(COUNTIFS($D$8:$D$108,D8,$F$8:$F$108,F8,$E$8:$E$108,E8)>1,"DUP","")
A9: ='01_BANK_RAW'!A6 | B9: ='01_BANK_RAW'!B6 | C9: ='01_BANK_RAW'!C6 | D9: ='01_BANK_RAW'!D6 | E9: =_xlfn.LET(t,SUBSTITUTE(TRIM(A9),".","/"),d,VALUE(LEFT(t,FIND("/",t)-1)),r,MID(t,FIND("/",t)+1,20),m,VALUE(LEFT(r,FIND("/",r)-1)),y,VALUE(MID(r,FIND("/",r)+1,4)),DATE(IF(y<100,2000+y,y),m,d)) | F9: =_xlfn.LET(t,SUBSTITUTE(C9,_xlfn.UNICHAR(160)," "),n,SUBSTITUTE(SUBSTITUTE(TRIM(t)," ",""),",",""),IF(LEFT(n,1)="(",-VALUE(SUBSTITUTE(SUBSTITUTE(n,"(",""),")","")),VALUE(n))) | G9: =TRIM(SUBSTITUTE(SUBSTITUTE(SUBSTITUTE(B9,_xlfn.UNICHAR(160)," "),_xlfn.UNICHAR(8207),""),_xlfn.UNICHAR(8206),"")) | H9: =IFERROR(INDEX(MAP[Acct],SUMPRODUCT(MATCH(1,--ISNUMBER(SEARCH(MAP[Keyword],G9)),0))),"UNMAPPED") | I9: =IF(COUNTIFS($D$8:$D$108,D9,$F$8:$F$108,F9,$E$8:$E$108,E9)>1,"DUP","")
A10: ='01_BANK_RAW'!A7 | B10: ='01_BANK_RAW'!B7 | C10: ='01_BANK_RAW'!C7 | D10: ='01_BANK_RAW'!D7 | E10: =_xlfn.LET(t,SUBSTITUTE(TRIM(A10),".","/"),d,VALUE(LEFT(t,FIND("/",t)-1)),r,MID(t,FIND("/",t)+1,20),m,VALUE(LEFT(r,FIND("/",r)-1)),y,VALUE(MID(r,FIND("/",r)+1,4)),DATE(IF(y<100,2000+y,y),m,d)) | F10: =_xlfn.LET(t,SUBSTITUTE(C10,_xlfn.UNICHAR(160)," "),n,SUBSTITUTE(SUBSTITUTE(TRIM(t)," ",""),",",""),IF(LEFT(n,1)="(",-VALUE(SUBSTITUTE(SUBSTITUTE(n,"(",""),")","")),VALUE(n))) | G10: =TRIM(SUBSTITUTE(SUBSTITUTE(SUBSTITUTE(B10,_xlfn.UNICHAR(160)," "),_xlfn.UNICHAR(8207),""),_xlfn.UNICHAR(8206),"")) | H10: =IFERROR(INDEX(MAP[Acct],SUMPRODUCT(MATCH(1,--ISNUMBER(SEARCH(MAP[Keyword],G10)),0))),"UNMAPPED") | I10: =IF(COUNTIFS($D$8:$D$108,D10,$F$8:$F$108,F10,$E$8:$E$108,E10)>1,"DUP","")
A11: ='01_BANK_RAW'!A8 | B11: ='01_BANK_RAW'!B8 | C11: ='01_BANK_RAW'!C8 | D11: ='01_BANK_RAW'!D8 | E11: =_xlfn.LET(t,SUBSTITUTE(TRIM(A11),".","/"),d,VALUE(LEFT(t,FIND("/",t)-1)),r,MID(t,FIND("/",t)+1,20),m,VALUE(LEFT(r,FIND("/",r)-1)),y,VALUE(MID(r,FIND("/",r)+1,4)),DATE(IF(y<100,2000+y,y),m,d)) | F11: =_xlfn.LET(t,SUBSTITUTE(C11,_xlfn.UNICHAR(160)," "),n,SUBSTITUTE(SUBSTITUTE(TRIM(t)," ",""),",",""),IF(LEFT(n,1)="(",-VALUE(SUBSTITUTE(SUBSTITUTE(n,"(",""),")","")),VALUE(n))) | G11: =TRIM(SUBSTITUTE(SUBSTITUTE(SUBSTITUTE(B11,_xlfn.UNICHAR(160)," "),_xlfn.UNICHAR(8207),""),_xlfn.UNICHAR(8206),"")) | H11: =IFERROR(INDEX(MAP[Acct],SUMPRODUCT(MATCH(1,--ISNUMBER(SEARCH(MAP[Keyword],G11)),0))),"UNMAPPED") | I11: =IF(COUNTIFS($D$8:$D$108,D11,$F$8:$F$108,F11,$E$8:$E$108,E11)>1,"DUP","")
A12: ='01_BANK_RAW'!A9 | B12: ='01_BANK_RAW'!B9 | C12: ='01_BANK_RAW'!C9 | D12: ='01_BANK_RAW'!D9 | E12: =_xlfn.LET(t,SUBSTITUTE(TRIM(A12),".","/"),d,VALUE(LEFT(t,FIND("/",t)-1)),r,MID(t,FIND("/",t)+1,20),m,VALUE(LEFT(r,FIND("/",r)-1)),y,VALUE(MID(r,FIND("/",r)+1,4)),DATE(IF(y<100,2000+y,y),m,d)) | F12: =_xlfn.LET(t,SUBSTITUTE(C12,_xlfn.UNICHAR(160)," "),n,SUBSTITUTE(SUBSTITUTE(TRIM(t)," ",""),",",""),IF(LEFT(n,1)="(",-VALUE(SUBSTITUTE(SUBSTITUTE(n,"(",""),")","")),VALUE(n))) | G12: =TRIM(SUBSTITUTE(SUBSTITUTE(SUBSTITUTE(B12,_xlfn.UNICHAR(160)," "),_xlfn.UNICHAR(8207),""),_xlfn.UNICHAR(8206),"")) | H12: =IFERROR(INDEX(MAP[Acct],SUMPRODUCT(MATCH(1,--ISNUMBER(SEARCH(MAP[Keyword],G12)),0))),"UNMAPPED") | I12: =IF(COUNTIFS($D$8:$D$108,D12,$F$8:$F$108,F12,$E$8:$E$108,E12)>1,"DUP","")
A13: ='01_BANK_RAW'!A10 | B13: ='01_BANK_RAW'!B10 | C13: ='01_BANK_RAW'!C10 | D13: ='01_BANK_RAW'!D10 | E13: =_xlfn.LET(t,SUBSTITUTE(TRIM(A13),".","/"),d,VALUE(LEFT(t,FIND("/",t)-1)),r,MID(t,FIND("/",t)+1,20),m,VALUE(LEFT(r,FIND("/",r)-1)),y,VALUE(MID(r,FIND("/",r)+1,4)),DATE(IF(y<100,2000+y,y),m,d)) | F13: =_xlfn.LET(t,SUBSTITUTE(C13,_xlfn.UNICHAR(160)," "),n,SUBSTITUTE(SUBSTITUTE(TRIM(t)," ",""),",",""),IF(LEFT(n,1)="(",-VALUE(SUBSTITUTE(SUBSTITUTE(n,"(",""),")","")),VALUE(n))) | G13: =TRIM(SUBSTITUTE(SUBSTITUTE(SUBSTITUTE(B13,_xlfn.UNICHAR(160)," "),_xlfn.UNICHAR(8207),""),_xlfn.UNICHAR(8206),"")) | H13: =IFERROR(INDEX(MAP[Acct],SUMPRODUCT(MATCH(1,--ISNUMBER(SEARCH(MAP[Keyword],G13)),0))),"UNMAPPED") | I13: =IF(COUNTIFS($D$8:$D$108,D13,$F$8:$F$108,F13,$E$8:$E$108,E13)>1,"DUP","")
A14: ='01_BANK_RAW'!A11 | B14: ='01_BANK_RAW'!B11 | C14: ='01_BANK_RAW'!C11 | D14: ='01_BANK_RAW'!D11 | E14: =_xlfn.LET(t,SUBSTITUTE(TRIM(A14),".","/"),d,VALUE(LEFT(t,FIND("/",t)-1)),r,MID(t,FIND("/",t)+1,20),m,VALUE(LEFT(r,FIND("/",r)-1)),y,VALUE(MID(r,FIND("/",r)+1,4)),DATE(IF(y<100,2000+y,y),m,d)) | F14: =_xlfn.LET(t,SUBSTITUTE(C14,_xlfn.UNICHAR(160)," "),n,SUBSTITUTE(SUBSTITUTE(TRIM(t)," ",""),",",""),IF(LEFT(n,1)="(",-VALUE(SUBSTITUTE(SUBSTITUTE(n,"(",""),")","")),VALUE(n))) | G14: =TRIM(SUBSTITUTE(SUBSTITUTE(SUBSTITUTE(B14,_xlfn.UNICHAR(160)," "),_xlfn.UNICHAR(8207),""),_xlfn.UNICHAR(8206),"")) | H14: =IFERROR(INDEX(MAP[Acct],SUMPRODUCT(MATCH(1,--ISNUMBER(SEARCH(MAP[Keyword],G14)),0))),"UNMAPPED") | I14: =IF(COUNTIFS($D$8:$D$108,D14,$F$8:$F$108,F14,$E$8:$E$108,E14)>1,"DUP","")
A15: ='01_BANK_RAW'!A12 | B15: ='01_BANK_RAW'!B12 | C15: ='01_BANK_RAW'!C12 | D15: ='01_BANK_RAW'!D12 | E15: =_xlfn.LET(t,SUBSTITUTE(TRIM(A15),".","/"),d,VALUE(LEFT(t,FIND("/",t)-1)),r,MID(t,FIND("/",t)+1,20),m,VALUE(LEFT(r,FIND("/",r)-1)),y,VALUE(MID(r,FIND("/",r)+1,4)),DATE(IF(y<100,2000+y,y),m,d)) | F15: =_xlfn.LET(t,SUBSTITUTE(C15,_xlfn.UNICHAR(160)," "),n,SUBSTITUTE(SUBSTITUTE(TRIM(t)," ",""),",",""),IF(LEFT(n,1)="(",-VALUE(SUBSTITUTE(SUBSTITUTE(n,"(",""),")","")),VALUE(n))) | G15: =TRIM(SUBSTITUTE(SUBSTITUTE(SUBSTITUTE(B15,_xlfn.UNICHAR(160)," "),_xlfn.UNICHAR(8207),""),_xlfn.UNICHAR(8206),"")) | H15: =IFERROR(INDEX(MAP[Acct],SUMPRODUCT(MATCH(1,--ISNUMBER(SEARCH(MAP[Keyword],G15)),0))),"UNMAPPED") | I15: =IF(COUNTIFS($D$8:$D$108,D15,$F$8:$F$108,F15,$E$8:$E$108,E15)>1,"DUP","")
A16: ='01_BANK_RAW'!A13 | B16: ='01_BANK_RAW'!B13 | C16: ='01_BANK_RAW'!C13 | D16: ='01_BANK_RAW'!D13 | E16: =_xlfn.LET(t,SUBSTITUTE(TRIM(A16),".","/"),d,VALUE(LEFT(t,FIND("/",t)-1)),r,MID(t,FIND("/",t)+1,20),m,VALUE(LEFT(r,FIND("/",r)-1)),y,VALUE(MID(r,FIND("/",r)+1,4)),DATE(IF(y<100,2000+y,y),m,d)) | F16: =_xlfn.LET(t,SUBSTITUTE(C16,_xlfn.UNICHAR(160)," "),n,SUBSTITUTE(SUBSTITUTE(TRIM(t)," ",""),",",""),IF(LEFT(n,1)="(",-VALUE(SUBSTITUTE(SUBSTITUTE(n,"(",""),")","")),VALUE(n))) | G16: =TRIM(SUBSTITUTE(SUBSTITUTE(SUBSTITUTE(B16,_xlfn.UNICHAR(160)," "),_xlfn.UNICHAR(8207),""),_xlfn.UNICHAR(8206),"")) | H16: =IFERROR(INDEX(MAP[Acct],SUMPRODUCT(MATCH(1,--ISNUMBER(SEARCH(MAP[Keyword],G16)),0))),"UNMAPPED") | I16: =IF(COUNTIFS($D$8:$D$108,D16,$F$8:$F$108,F16,$E$8:$E$108,E16)>1,"DUP","")
A17: ='01_BANK_RAW'!A14 | B17: ='01_BANK_RAW'!B14 | C17: ='01_BANK_RAW'!C14 | D17: ='01_BANK_RAW'!D14 | E17: =_xlfn.LET(t,SUBSTITUTE(TRIM(A17),".","/"),d,VALUE(LEFT(t,FIND("/",t)-1)),r,MID(t,FIND("/",t)+1,20),m,VALUE(LEFT(r,FIND("/",r)-1)),y,VALUE(MID(r,FIND("/",r)+1,4)),DATE(IF(y<100,2000+y,y),m,d)) | F17: =_xlfn.LET(t,SUBSTITUTE(C17,_xlfn.UNICHAR(160)," "),n,SUBSTITUTE(SUBSTITUTE(TRIM(t)," ",""),",",""),IF(LEFT(n,1)="(",-VALUE(SUBSTITUTE(SUBSTITUTE(n,"(",""),")","")),VALUE(n))) | G17: =TRIM(SUBSTITUTE(SUBSTITUTE(SUBSTITUTE(B17,_xlfn.UNICHAR(160)," "),_xlfn.UNICHAR(8207),""),_xlfn.UNICHAR(8206),"")) | H17: =IFERROR(INDEX(MAP[Acct],SUMPRODUCT(MATCH(1,--ISNUMBER(SEARCH(MAP[Keyword],G17)),0))),"UNMAPPED") | I17: =IF(COUNTIFS($D$8:$D$108,D17,$F$8:$F$108,F17,$E$8:$E$108,E17)>1,"DUP","")
A18: ='01_BANK_RAW'!A15 | B18: ='01_BANK_RAW'!B15 | C18: ='01_BANK_RAW'!C15 | D18: ='01_BANK_RAW'!D15 | E18: =_xlfn.LET(t,SUBSTITUTE(TRIM(A18),".","/"),d,VALUE(LEFT(t,FIND("/",t)-1)),r,MID(t,FIND("/",t)+1,20),m,VALUE(LEFT(r,FIND("/",r)-1)),y,VALUE(MID(r,FIND("/",r)+1,4)),DATE(IF(y<100,2000+y,y),m,d)) | F18: =_xlfn.LET(t,SUBSTITUTE(C18,_xlfn.UNICHAR(160)," "),n,SUBSTITUTE(SUBSTITUTE(TRIM(t)," ",""),",",""),IF(LEFT(n,1)="(",-VALUE(SUBSTITUTE(SUBSTITUTE(n,"(",""),")","")),VALUE(n))) | G18: =TRIM(SUBSTITUTE(SUBSTITUTE(SUBSTITUTE(B18,_xlfn.UNICHAR(160)," "),_xlfn.UNICHAR(8207),""),_xlfn.UNICHAR(8206),"")) | H18: =IFERROR(INDEX(MAP[Acct],SUMPRODUCT(MATCH(1,--ISNUMBER(SEARCH(MAP[Keyword],G18)),0))),"UNMAPPED") | I18: =IF(COUNTIFS($D$8:$D$108,D18,$F$8:$F$108,F18,$E$8:$E$108,E18)>1,"DUP","")
A19: ='01_BANK_RAW'!A16 | B19: ='01_BANK_RAW'!B16 | C19: ='01_BANK_RAW'!C16 | D19: ='01_BANK_RAW'!D16 | E19: =_xlfn.LET(t,SUBSTITUTE(TRIM(A19),".","/"),d,VALUE(LEFT(t,FIND("/",t)-1)),r,MID(t,FIND("/",t)+1,20),m,VALUE(LEFT(r,FIND("/",r)-1)),y,VALUE(MID(r,FIND("/",r)+1,4)),DATE(IF(y<100,2000+y,y),m,d)) | F19: =_xlfn.LET(t,SUBSTITUTE(C19,_xlfn.UNICHAR(160)," "),n,SUBSTITUTE(SUBSTITUTE(TRIM(t)," ",""),",",""),IF(LEFT(n,1)="(",-VALUE(SUBSTITUTE(SUBSTITUTE(n,"(",""),")","")),VALUE(n))) | G19: =TRIM(SUBSTITUTE(SUBSTITUTE(SUBSTITUTE(B19,_xlfn.UNICHAR(160)," "),_xlfn.UNICHAR(8207),""),_xlfn.UNICHAR(8206),"")) | H19: =IFERROR(INDEX(MAP[Acct],SUMPRODUCT(MATCH(1,--ISNUMBER(SEARCH(MAP[Keyword],G19)),0))),"UNMAPPED") | I19: =IF(COUNTIFS($D$8:$D$108,D19,$F$8:$F$108,F19,$E$8:$E$108,E19)>1,"DUP","")
... A108: ='01_BANK_RAW'!A105 | B108: ='01_BANK_RAW'!B105 | C108: ='01_BANK_RAW'!C105 | D108: ='01_BANK_RAW'!D105 | E108: =_xlfn.LET(t,SUBSTITUTE(TRIM(A108),".","/"),d,VALUE(LEFT(t,FIND("/",t)-1)),r,MID(t,FIND("/",t)+1,20),m,VALUE(LEFT(r,FIND("/",r)-1)),y,VALUE(MID(r,FIND("/",r)+1,4)),DATE(IF(y<100,2000+y,y),m,d)) | F108: =_xlfn.LET(t,SUBSTITUTE(C108,_xlfn.UNICHAR(160)," "),n,SUBSTITUTE(SUBSTITUTE(TRIM(t)," ",""),",",""),IF(LEFT(n,1)="(",-VALUE(SUBSTITUTE(SUBSTITUTE(n,"(",""),")","")),VALUE(n))) | G108: =TRIM(SUBSTITUTE(SUBSTITUTE(SUBSTITUTE(B108,_xlfn.UNICHAR(160)," "),_xlfn.UNICHAR(8207),""),_xlfn.UNICHAR(8206),"")) | H108: =IFERROR(INDEX(MAP[Acct],SUMPRODUCT(MATCH(1,--ISNUMBER(SEARCH(MAP[Keyword],G108)),0))),"UNMAPPED") | I108: =IF(COUNTIFS($D$8:$D$108,D108,$F$8:$F$108,F108,$E$8:$E$108,E108)>1,"DUP","")
A111: בקרת איכות הניקוי
A112: שורות שנקלטו | B112: =COUNTA(D8:D108)
A113: שורות שלא סווגו | B113: =COUNTIF(H8:H108,"UNMAPPED")
A114: שורות שסומנו ככפילות | B114: =COUNTIF(I8:I108,"DUP")
A115: סה"כ תקבולים בקובץ, ללא כפילויות | B115: =SUMIFS(F8:F108,I8:I108,"",F8:F108,">0")
A116: סה"כ תשלומים בקובץ, ללא כפילויות | B116: =SUMIFS(F8:F108,I8:I108,"",F8:F108,"<0")
A117: סה"כ תשלומי מס בתקופה | B117: =SUMIFS(F8:F108,H8:H108,"TAX",I8:I108,"")
A118: משיכות בעלים, דגל לסעיף 3(ט1) | B118: =SUMIFS(F8:F108,H8:H108,"OWNER",I8:I108,"")
A121: מקרא הקודים
A122: UNMAPPED | B122: לא נמצאה מילת מפתח מתאימה
A123: DUP | B123: השורה מופיעה יותר מפעם אחת
A124: TAX | B124: תשלומי מס
A125: OWNER | B125: משיכות בעלים
A127: הקובץ הוא מדגם תנועות בנק לחצי שנה לצורך תרגול ניקוי, ולא דוח תזרים מלא. שורת משיכות הבעלים היא הדגל האדום: משיכה שמצטברת ביוני ניתנת עוד לתיקון, אותה משיכה שמתגלה במרץ שאחרי היא כבר חבות מס.

Sheet 05_BUDGET
A1: Budget 2026 · התקציב המאושר
A2: אושר בדצמבר 2025 ולא עודכן מאז. בדיוק הבעיה שמעבדה 6 פותרת.
A4: Month | B4: MonthName | C4: Dept | D4: DeptName | E4: Grp | F4: GrpName | G4: Acct | H4: AcctName | I4: Budget
A5: 1 | B5: Jan | C5: SALES | D5: Direct Sales | E5: REVENUE | F5: Revenue | G5: REVENUE_PROD | H5: Product Revenue | I5: 491040
A6: 1 | B6: Jan | C6: CHANNEL | D6: Distributor Channel | E6: REVENUE | F6: Revenue | G6: REVENUE_PROD | H6: Product Revenue | I6: 267840
A7: 1 | B7: Jan | C7: SERVICE | D7: Service and Support | E7: REVENUE | F7: Revenue | G7: REVENUE_PROD | H7: Product Revenue | I7: 133920
A8: 1 | B8: Jan | C8: SALES | D8: Direct Sales | E8: REVENUE | F8: Revenue | G8: REVENUE_SVC | H8: Service Revenue | I8: 4140
A9: 1 | B9: Jan | C9: CHANNEL | D9: Distributor Channel | E9: REVENUE | F9: Revenue | G9: REVENUE_SVC | H9: Service Revenue | I9: 4140
A10: 1 | B10: Jan | C10: SERVICE | D10: Service and Support | E10: REVENUE | F10: Revenue | G10: REVENUE_SVC | H10: Service Revenue | I10: 74520
A11: 1 | B11: Jan | C11: SALES | D11: Direct Sales | E11: COGS | F11: Cost of Sales | G11: COGS | H11: Cost of Goods Sold | I11: 319176
A12: 1 | B12: Jan | C12: CHANNEL | D12: Distributor Channel | E12: COGS | F12: Cost of Sales | G12: COGS | H12: Cost of Goods Sold | I12: 174096
A13: 1 | B13: Jan | C13: SERVICE | D13: Service and Support | E13: COGS | F13: Cost of Sales | G13: COGS | H13: Cost of Goods Sold | I13: 87048
A14: 1 | B14: Jan | C14: SALES | D14: Direct Sales | E14: OPEX | F14: Operating Expenses | G14: SALARY | H14: Payroll | I14: 81180
A15: 1 | B15: Jan | C15: CHANNEL | D15: Distributor Channel | E15: OPEX | F15: Operating Expenses | G15: SALARY | H15: Payroll | I15: 44280
A16: 1 | B16: Jan | C16: SERVICE | D16: Service and Support | E16: OPEX | F16: Operating Expenses | G16: SALARY | H16: Payroll | I16: 22140
... A472: 12 | B472: Dec | C472: SERVICE | D472: Service and Support | E472: OPEX | F472: Operating Expenses | G472: FINANCE | H472: Finance Costs | I472: 3263

Sheet 10_CONTROL
A1: Lab 2 · לוח בקרת ביצוע מול תקציב
A2: SUMIFS הוא מנוע הבקרה. בחרו מחלקה ותקופה למעלה, והלוח כולו מתעדכן.
A3: Dept (מחלקה): | B3: ALL
A4: FromMonth (מחודש): | B4: 1
A5: ToMonth (עד חודש): | B5: 6
A7: Acct | B7: AcctName | C7: Grp | D7: Budget | E7: Actual | F7: Var | G7: VarPct | H7: Flag | I7: PctOfRevenue
A8: REVENUE_PROD | B8: Product Revenue | C8: REVENUE | D8: =SUMIFS(BUDGET[Budget],BUDGET[Acct],$A8,BUDGET[Month],">="&$B$4,BUDGET[Month],"<="&$B$5,BUDGET[Dept],IF($B$3="ALL","*",$B$3)) | E8: =SUMIFS(GL[Amount],GL[Acct],$A8,GL[Month],">="&$B$4,GL[Month],"<="&$B$5,GL[Dept],IF($B$3="ALL","*",$B$3)) | F8: =E8-D8 | G8: =IFERROR(F8/D8,0) | H8: =IF(ABS(G8)>10%,IF($C8="REVENUE",IF(G8<0,"MISS","BEAT"),IF(G8>0,"OVER","SAVE")),"") | I8: =IFERROR(E8/SUMIFS(GL[Amount],GL[Grp],"REVENUE",GL[Month],">="&$B$4,GL[Month],"<="&$B$5,GL[Dept],IF($B$3="ALL","*",$B$3)),0)
A9: REVENUE_SVC | B9: Service Revenue | C9: REVENUE | D9: =SUMIFS(BUDGET[Budget],BUDGET[Acct],$A9,BUDGET[Month],">="&$B$4,BUDGET[Month],"<="&$B$5,BUDGET[Dept],IF($B$3="ALL","*",$B$3)) | E9: =SUMIFS(GL[Amount],GL[Acct],$A9,GL[Month],">="&$B$4,GL[Month],"<="&$B$5,GL[Dept],IF($B$3="ALL","*",$B$3)) | F9: =E9-D9 | G9: =IFERROR(F9/D9,0) | H9: =IF(ABS(G9)>10%,IF($C9="REVENUE",IF(G9<0,"MISS","BEAT"),IF(G9>0,"OVER","SAVE")),"") | I9: =IFERROR(E9/SUMIFS(GL[Amount],GL[Grp],"REVENUE",GL[Month],">="&$B$4,GL[Month],"<="&$B$5,GL[Dept],IF($B$3="ALL","*",$B$3)),0)
A10: COGS | B10: Cost of Goods Sold | C10: COGS | D10: =SUMIFS(BUDGET[Budget],BUDGET[Acct],$A10,BUDGET[Month],">="&$B$4,BUDGET[Month],"<="&$B$5,BUDGET[Dept],IF($B$3="ALL","*",$B$3)) | E10: =SUMIFS(GL[Amount],GL[Acct],$A10,GL[Month],">="&$B$4,GL[Month],"<="&$B$5,GL[Dept],IF($B$3="ALL","*",$B$3)) | F10: =E10-D10 | G10: =IFERROR(F10/D10,0) | H10: =IF(ABS(G10)>10%,IF($C10="REVENUE",IF(G10<0,"MISS","BEAT"),IF(G10>0,"OVER","SAVE")),"") | I10: =IFERROR(E10/SUMIFS(GL[Amount],GL[Grp],"REVENUE",GL[Month],">="&$B$4,GL[Month],"<="&$B$5,GL[Dept],IF($B$3="ALL","*",$B$3)),0)
A11: SALARY | B11: Payroll | C11: OPEX | D11: =SUMIFS(BUDGET[Budget],BUDGET[Acct],$A11,BUDGET[Month],">="&$B$4,BUDGET[Month],"<="&$B$5,BUDGET[Dept],IF($B$3="ALL","*",$B$3)) | E11: =SUMIFS(GL[Amount],GL[Acct],$A11,GL[Month],">="&$B$4,GL[Month],"<="&$B$5,GL[Dept],IF($B$3="ALL","*",$B$3)) | F11: =E11-D11 | G11: =IFERROR(F11/D11,0) | H11: =IF(ABS(G11)>10%,IF($C11="REVENUE",IF(G11<0,"MISS","BEAT"),IF(G11>0,"OVER","SAVE")),"") | I11: =IFERROR(E11/SUMIFS(GL[Amount],GL[Grp],"REVENUE",GL[Month],">="&$B$4,GL[Month],"<="&$B$5,GL[Dept],IF($B$3="ALL","*",$B$3)),0)
A12: RENT | B12: Rent and Facilities | C12: OPEX | D12: =SUMIFS(BUDGET[Budget],BUDGET[Acct],$A12,BUDGET[Month],">="&$B$4,BUDGET[Month],"<="&$B$5,BUDGET[Dept],IF($B$3="ALL","*",$B$3)) | E12: =SUMIFS(GL[Amount],GL[Acct],$A12,GL[Month],">="&$B$4,GL[Month],"<="&$B$5,GL[Dept],IF($B$3="ALL","*",$B$3)) | F12: =E12-D12 | G12: =IFERROR(F12/D12,0) | H12: =IF(ABS(G12)>10%,IF($C12="REVENUE",IF(G12<0,"MISS","BEAT"),IF(G12>0,"OVER","SAVE")),"") | I12: =IFERROR(E12/SUMIFS(GL[Amount],GL[Grp],"REVENUE",GL[Month],">="&$B$4,GL[Month],"<="&$B$5,GL[Dept],IF($B$3="ALL","*",$B$3)),0)
A13: VEHICLE | B13: Vehicle | C13: OPEX | D13: =SUMIFS(BUDGET[Budget],BUDGET[Acct],$A13,BUDGET[Month],">="&$B$4,BUDGET[Month],"<="&$B$5,BUDGET[Dept],IF($B$3="ALL","*",$B$3)) | E13: =SUMIFS(GL[Amount],GL[Acct],$A13,GL[Month],">="&$B$4,GL[Month],"<="&$B$5,GL[Dept],IF($B$3="ALL","*",$B$3)) | F13: =E13-D13 | G13: =IFERROR(F13/D13,0) | H13: =IF(ABS(G13)>10%,IF($C13="REVENUE",IF(G13<0,"MISS","BEAT"),IF(G13>0,"OVER","SAVE")),"") | I13: =IFERROR(E13/SUMIFS(GL[Amount],GL[Grp],"REVENUE",GL[Month],">="&$B$4,GL[Month],"<="&$B$5,GL[Dept],IF($B$3="ALL","*",$B$3)),0)
A14: MARKETING | B14: Marketing | C14: OPEX | D14: =SUMIFS(BUDGET[Budget],BUDGET[Acct],$A14,BUDGET[Month],">="&$B$4,BUDGET[Month],"<="&$B$5,BUDGET[Dept],IF($B$3="ALL","*",$B$3)) | E14: =SUMIFS(GL[Amount],GL[Acct],$A14,GL[Month],">="&$B$4,GL[Month],"<="&$B$5,GL[Dept],IF($B$3="ALL","*",$B$3)) | F14: =E14-D14 | G14: =IFERROR(F14/D14,0) | H14: =IF(ABS(G14)>10%,IF($C14="REVENUE",IF(G14<0,"MISS","BEAT"),IF(G14>0,"OVER","SAVE")),"") | I14: =IFERROR(E14/SUMIFS(GL[Amount],GL[Grp],"REVENUE",GL[Month],">="&$B$4,GL[Month],"<="&$B$5,GL[Dept],IF($B$3="ALL","*",$B$3)),0)
A15: ENTERTAIN | B15: Entertainment | C15: OPEX | D15: =SUMIFS(BUDGET[Budget],BUDGET[Acct],$A15,BUDGET[Month],">="&$B$4,BUDGET[Month],"<="&$B$5,BUDGET[Dept],IF($B$3="ALL","*",$B$3)) | E15: =SUMIFS(GL[Amount],GL[Acct],$A15,GL[Month],">="&$B$4,GL[Month],"<="&$B$5,GL[Dept],IF($B$3="ALL","*",$B$3)) | F15: =E15-D15 | G15: =IFERROR(F15/D15,0) | H15: =IF(ABS(G15)>10%,IF($C15="REVENUE",IF(G15<0,"MISS","BEAT"),IF(G15>0,"OVER","SAVE")),"") | I15: =IFERROR(E15/SUMIFS(GL[Amount],GL[Grp],"REVENUE",GL[Month],">="&$B$4,GL[Month],"<="&$B$5,GL[Dept],IF($B$3="ALL","*",$B$3)),0)
A16: OFFICE | B16: Office | C16: OPEX | D16: =SUMIFS(BUDGET[Budget],BUDGET[Acct],$A16,BUDGET[Month],">="&$B$4,BUDGET[Month],"<="&$B$5,BUDGET[Dept],IF($B$3="ALL","*",$B$3)) | E16: =SUMIFS(GL[Amount],GL[Acct],$A16,GL[Month],">="&$B$4,GL[Month],"<="&$B$5,GL[Dept],IF($B$3="ALL","*",$B$3)) | F16: =E16-D16 | G16: =IFERROR(F16/D16,0) | H16: =IF(ABS(G16)>10%,IF($C16="REVENUE",IF(G16<0,"MISS","BEAT"),IF(G16>0,"OVER","SAVE")),"") | I16: =IFERROR(E16/SUMIFS(GL[Amount],GL[Grp],"REVENUE",GL[Month],">="&$B$4,GL[Month],"<="&$B$5,GL[Dept],IF($B$3="ALL","*",$B$3)),0)
A17: MERCHANT | B17: Merchant Fees | C17: OPEX | D17: =SUMIFS(BUDGET[Budget],BUDGET[Acct],$A17,BUDGET[Month],">="&$B$4,BUDGET[Month],"<="&$B$5,BUDGET[Dept],IF($B$3="ALL","*",$B$3)) | E17: =SUMIFS(GL[Amount],GL[Acct],$A17,GL[Month],">="&$B$4,GL[Month],"<="&$B$5,GL[Dept],IF($B$3="ALL","*",$B$3)) | F17: =E17-D17 | G17: =IFERROR(F17/D17,0) | H17: =IF(ABS(G17)>10%,IF($C17="REVENUE",IF(G17<0,"MISS","BEAT"),IF(G17>0,"OVER","SAVE")),"") | I17: =IFERROR(E17/SUMIFS(GL[Amount],GL[Grp],"REVENUE",GL[Month],">="&$B$4,GL[Month],"<="&$B$5,GL[Dept],IF($B$3="ALL","*",$B$3)),0)
A18: PROFSVC | B18: Professional Fees | C18: OPEX | D18: =SUMIFS(BUDGET[Budget],BUDGET[Acct],$A18,BUDGET[Month],">="&$B$4,BUDGET[Month],"<="&$B$5,BUDGET[Dept],IF($B$3="ALL","*",$B$3)) | E18: =SUMIFS(GL[Amount],GL[Acct],$A18,GL[Month],">="&$B$4,GL[Month],"<="&$B$5,GL[Dept],IF($B$3="ALL","*",$B$3)) | F18: =E18-D18 | G18: =IFERROR(F18/D18,0) | H18: =IF(ABS(G18)>10%,IF($C18="REVENUE",IF(G18<0,"MISS","BEAT"),IF(G18>0,"OVER","SAVE")),"") | I18: =IFERROR(E18/SUMIFS(GL[Amount],GL[Grp],"REVENUE",GL[Month],">="&$B$4,GL[Month],"<="&$B$5,GL[Dept],IF($B$3="ALL","*",$B$3)),0)
A19: DEPREC | B19: Depreciation | C19: OPEX | D19: =SUMIFS(BUDGET[Budget],BUDGET[Acct],$A19,BUDGET[Month],">="&$B$4,BUDGET[Month],"<="&$B$5,BUDGET[Dept],IF($B$3="ALL","*",$B$3)) | E19: =SUMIFS(GL[Amount],GL[Acct],$A19,GL[Month],">="&$B$4,GL[Month],"<="&$B$5,GL[Dept],IF($B$3="ALL","*",$B$3)) | F19: =E19-D19 | G19: =IFERROR(F19/D19,0) | H19: =IF(ABS(G19)>10%,IF($C19="REVENUE",IF(G19<0,"MISS","BEAT"),IF(G19>0,"OVER","SAVE")),"") | I19: =IFERROR(E19/SUMIFS(GL[Amount],GL[Grp],"REVENUE",GL[Month],">="&$B$4,GL[Month],"<="&$B$5,GL[Dept],IF($B$3="ALL","*",$B$3)),0)
A20: FINANCE | B20: Finance Costs | C20: OPEX | D20: =SUMIFS(BUDGET[Budget],BUDGET[Acct],$A20,BUDGET[Month],">="&$B$4,BUDGET[Month],"<="&$B$5,BUDGET[Dept],IF($B$3="ALL","*",$B$3)) | E20: =SUMIFS(GL[Amount],GL[Acct],$A20,GL[Month],">="&$B$4,GL[Month],"<="&$B$5,GL[Dept],IF($B$3="ALL","*",$B$3)) | F20: =E20-D20 | G20: =IFERROR(F20/D20,0) | H20: =IF(ABS(G20)>10%,IF($C20="REVENUE",IF(G20<0,"MISS","BEAT"),IF(G20>0,"OVER","SAVE")),"") | I20: =IFERROR(E20/SUMIFS(GL[Amount],GL[Grp],"REVENUE",GL[Month],">="&$B$4,GL[Month],"<="&$B$5,GL[Dept],IF($B$3="ALL","*",$B$3)),0)
A23: מדדי מפתח לתקופה
A24: מחזור בפועל | B24: =SUMIFS(GL[Amount],GL[Grp],"REVENUE",GL[Month],">="&$B$4,GL[Month],"<="&$B$5,GL[Dept],IF($B$3="ALL","*",$B$3))
A25: עלות המכר בפועל | B25: =SUMIFS(GL[Amount],GL[Grp],"COGS",GL[Month],">="&$B$4,GL[Month],"<="&$B$5,GL[Dept],IF($B$3="ALL","*",$B$3))
A26: רווח גולמי | B26: =B24-B25
A27: שיעור רווח גולמי בפועל | B27: =IFERROR(B26/B24,0)
A28: שיעור רווח גולמי בתקציב | B28: =IFERROR((SUMIFS(BUDGET[Budget],BUDGET[Grp],"REVENUE",BUDGET[Month],">="&$B$4,BUDGET[Month],"<="&$B$5)-SUMIFS(BUDGET[Budget],BUDGET[Grp],"COGS",BUDGET[Month],">="&$B$4,BUDGET[Month],"<="&$B$5))/SUMIFS(BUDGET[Budget],BUDGET[Grp],"REVENUE",BUDGET[Month],">="&$B$4,BUDGET[Month],"<="&$B$5),0)
A29: פער שיעור הרווח הגולמי, נקודות אחוז | B29: =B27-B28
A30: רווח תפעולי בפועל | B30: =B26-SUMIFS(GL[Amount],GL[Grp],"OPEX",GL[Month],">="&$B$4,GL[Month],"<="&$B$5,GL[Dept],IF($B$3="ALL","*",$B$3))
A32: מקרא הקודים
A33: OVER | B33: חריגה בהוצאה מעל 10%
A34: SAVE | B34: חיסכון בהוצאה מעל 10%
A35: MISS | B35: פספוס הכנסה מעל 10%
A36: BEAT | B36: עמידה מעל היעד ביותר מ-10%
A37: ALL | B37: כל המחלקות יחד
A39: שורת פער שיעור הרווח הגולמי היא המדד שפקיד השומה בודק ראשון. סטייה של יותר מנקודת אחוז אחת מהשנה הקודמת או מהענף היא הטריגר הנפוץ ביותר לשומה לפי מיטב השפיטה. עדיף לגלות אותה ברבעון ולא בדיון.
A40: הגרף מימין מתעדכן ברגע שתמלאו את העמודות. זו הנקודה שבה טבלה הופכת לתמונה, ובה מנהל מבין תוך שתי שניות מה שבטבלה לוקח לו דקה.

Sheet 11_PVM
A1: Lab 3 · פירוק הסטייה: מחיר, כמות ותמהיל
A2: ״ההכנסות מתחת לתקציב״ אינה תשובה. התשובה היא כמה מזה מחיר, כמה כמות וכמה תמהיל.
A7: Product | B7: ProductName | C7: BudQty | D7: BudPrice | E7: BudRev | F7: ActQty | G7: ActPrice | H7: ActRev | I7: TotalVar | J7: PriceVar | K7: VolumeVar | L7: MixVar
A8: PRINTERS | B8: Printers | C8: 1180 | D8: 3250 | E8: =C8*D8 | F8: 1042 | G8: 3095 | H8: =F8*G8 | I8: =H8-E8 | J8: =(G8-D8)*F8 | K8: =($F$12-$C$12)*(C8/$C$12)*D8 | L8: =(F8-$F$12*(C8/$C$12))*D8
A9: MONITORS | B9: Monitors | C9: 2640 | D9: 1480 | E9: =C9*D9 | F9: 2905 | G9: 1425 | H9: =F9*G9 | I9: =H9-E9 | J9: =(G9-D9)*F9 | K9: =($F$12-$C$12)*(C9/$C$12)*D9 | L9: =(F9-$F$12*(C9/$C$12))*D9
A10: ACCESS | B10: Accessories | C10: 9800 | D10: 168 | E10: =C10*D10 | F10: 11450 | G10: 159 | H10: =F10*G10 | I10: =H10-E10 | J10: =(G10-D10)*F10 | K10: =($F$12-$C$12)*(C10/$C$12)*D10 | L10: =(F10-$F$12*(C10/$C$12))*D10
A11: SERVICE | B11: Service and Warranty | C11: 640 | D11: 1800 | E11: =C11*D11 | F11: 588 | G11: 1955 | H11: =F11*G11 | I11: =H11-E11 | J11: =(G11-D11)*F11 | K11: =($F$12-$C$12)*(C11/$C$12)*D11 | L11: =(F11-$F$12*(C11/$C$12))*D11
A12: TOTAL | C12: =SUM(C8:C11) | E12: =SUM(E8:E11) | F12: =SUM(F8:F11) | H12: =SUM(H8:H11) | I12: =SUM(I8:I11) | J12: =SUM(J8:J11) | K12: =SUM(K8:K11) | L12: =SUM(L8:L11)
A14: בדיקת האמת: פער מחיר ועוד פער כמות ועוד פער תמהיל שווים בדיוק לסטייה הכוללת. אם לא, יש טעות באחד השלושה.
A15: קריאת התוצאה: הכמות הכוללת עלתה ולכן פער הכמות חיובי, אבל פער התמהיל שלילי בסדר גודל דומה, כי הגידול הגיע מאביזרים בשקלים בודדים ולא ממדפסות. בתוספת הנחות המחיר, התוצאה נטו שלילית. ללקוח צריך להגיד: המכירות גדלו והרווח ירד, וזו לא סתירה.
A16: אזהרה מקצועית: החישוב מסכם יחידות של מוצרים שמחיריהם שונים פי עשרים. זו הסיבה שפער התמהיל יוצא גדול, וזו התובנה ולא תקלה. מול לקוח אמיתי ודאו שהוא מבין שאלה מספרי הסבר ולא מדידה.

Sheet 20_WORKCAP
A1: Lab 4 · הון חוזר ומחזור המזומן
A2: שלושה מספרים שמסבירים למה חברה רווחית יכולה להיות בלי מזומן.
A7: Month | B7: MonthName | C7: Revenue | D7: COGS | E7: AR | F7: AP | G7: Inventory | H7: DSO | I7: DPO | J7: DIO | K7: CCC
A8: 1 | B8: Jan | C8: 987371 | D8: 609068 | E8: 2145103 | F8: 806162 | G8: 997674 | H8: =IFERROR(E8/C8*30,0) | I8: =IFERROR(F8/D8*30,0) | J8: =IFERROR(G8/D8*30,0) | K8: =H8+J8-I8
A9: 2 | B9: Feb | C9: 959952 | D9: 588672 | E9: 2161448 | F9: 952386 | G9: 1048375 | H9: =IFERROR(E9/C9*30,0) | I9: =IFERROR(F9/D9*30,0) | J9: =IFERROR(G9/D9*30,0) | K9: =H9+J9-I9
A10: 3 | B10: Mar | C10: 1176314 | D10: 724896 | E10: 2792225 | F10: 1093584 | G10: 1169237 | H10: =IFERROR(E10/C10*30,0) | I10: =IFERROR(F10/D10*30,0) | J10: =IFERROR(G10/D10*30,0) | K10: =H10+J10-I10
A11: 4 | B11: Apr | C11: 1069254 | D11: 655706 | E11: 2575637 | F11: 1068741 | G11: 1034082 | H11: =IFERROR(E11/C11*30,0) | I11: =IFERROR(F11/D11*30,0) | J11: =IFERROR(G11/D11*30,0) | K11: =H11+J11-I11
A12: 5 | B12: May | C12: 1072789 | D12: 660380 | E12: 2571705 | F12: 859339 | G12: 1159433 | H12: =IFERROR(E12/C12*30,0) | I12: =IFERROR(F12/D12*30,0) | J12: =IFERROR(G12/D12*30,0) | K12: =H12+J12-I12
A13: 6 | B13: Jun | C13: 1233218 | D13: 734894 | E13: 3121443 | F13: 1244699 | G13: 1104023 | H13: =IFERROR(E13/C13*30,0) | I13: =IFERROR(F13/D13*30,0) | J13: =IFERROR(G13/D13*30,0) | K13: =H13+J13-I13
A14: 7 | B14: Jul | C14: 985181 | D14: 605171 | E14: 2366819 | F14: 889482 | G14: 1121343 | H14: =IFERROR(E14/C14*30,0) | I14: =IFERROR(F14/D14*30,0) | J14: =IFERROR(G14/D14*30,0) | K14: =H14+J14-I14
A15: 8 | B15: Aug | C15: 932546 | D15: 546524 | E15: 2402910 | F15: 817834 | G15: 894733 | H15: =IFERROR(E15/C15*30,0) | I15: =IFERROR(F15/D15*30,0) | J15: =IFERROR(G15/D15*30,0) | K15: =H15+J15-I15
A16: 9 | B16: Sep | C16: 1234550 | D16: 727622 | E16: 2938571 | F16: 1180471 | G16: 1210551 | H16: =IFERROR(E16/C16*30,0) | I16: =IFERROR(F16/D16*30,0) | J16: =IFERROR(G16/D16*30,0) | K16: =H16+J16-I16
A17: 10 | B17: Oct | C17: 1236841 | D17: 738154 | E17: 2882123 | F17: 973854 | G17: 1234440 | H17: =IFERROR(E17/C17*30,0) | I17: =IFERROR(F17/D17*30,0) | J17: =IFERROR(G17/D17*30,0) | K17: =H17+J17-I17
A18: 11 | B18: Nov | C18: 1236810 | D18: 759323 | E18: 2831335 | F18: 1104857 | G18: 1257691 | H18: =IFERROR(E18/C18*30,0) | I18: =IFERROR(F18/D18*30,0) | J18: =IFERROR(G18/D18*30,0) | K18: =H18+J18-I18
A19: 12 | B19: Dec | C19: 1455057 | D19: 906067 | E19: 3167889 | F19: 1258289 | G19: 1537162 | H19: =IFERROR(E19/C19*30,0) | I19: =IFERROR(F19/D19*30,0) | J19: =IFERROR(G19/D19*30,0) | K19: =H19+J19-I19
A22: הלֶבֶר: כמה שווה יום אחד
A23: ממוצע DSO שנתי, ימים | B23: =AVERAGE(H8:H19)
A24: ממוצע CCC שנתי, ימים | B24: =AVERAGE(K8:K19)
A25: מחזור יומי ממוצע | B25: =SUM(C8:C19)/365
A26: שווי קיצור יום גבייה אחד | B26: =B25
A27: יעד קיצור DSO בימים, שנו את המספר | B27: 7
A28: מזומן שישתחרר מיד | B28: =B25*B27
A29: חיסכון ריבית שנתי בריבית 8% | B29: =B28*8%
A32: יתרת בעלים, הדגל של מודול ב׳
A33: יתרת בעלים לסוף השנה | B33: 486000
A34: מועד החיוב לפי סעיף 3(ט1) | B34: End of the year following the drawing year
A36: יתרת בעלים היא הון חוזר לכל דבר, רק שהיא ממומנת על ידי החברה ומייצרת חבות מס. כשגם ה-CCC גבוה וגם יתרת הבעלים גבוהה, החברה מממנת במקביל את הלקוחות ואת הבעלים, וזו הנקודה שבה נגמרת המסגרת בבנק.

Sheet 30_CASH13
A1: Lab 5 · תזרים מזומנים ל-13 שבועות
A2: 13 שבועות הם רבעון. מספיק רחוק כדי להספיק לפעול, מספיק קרוב כדי שהמספרים יהיו אמיתיים.
A4: Scenario (תרחיש): | B4: BASE
A5: Opening (יתרת פתיחה): | B5: 285000
A6: Facility (מסגרת אשראי): | B6: 600000
A9: Line | B9: LineName | C9: Conf | D9: W1 05/07 | E9: W2 12/07 | F9: W3 19/07 | G9: W4 26/07 | H9: W5 02/08 | I9: W6 09/08 | J9: W7 16/08 | K9: W8 23/08 | L9: W9 30/08 | M9: W10 06/09 | N9: W11 13/09 | O9: W12 20/09 | P9: W13 27/09 | Q9: Total
A10: AR_CONTRACT | B10: Customer receipts, fixed contracts | C10: 5 | D10: 180000 | E10: 180000 | F10: 180000 | G10: 180000 | H10: 180000 | I10: 180000 | J10: 180000 | K10: 180000 | L10: 180000 | M10: 180000 | N10: 180000 | O10: 180000 | P10: 180000
A11: AR_OPEN | B11: Customer receipts, open orders | C11: 3 | D11: 120000 | E11: 90000 | F11: 140000 | G11: 110000 | H11: 95000 | I11: 130000 | J11: 105000 | K11: 88000 | L11: 145000 | M11: 120000 | N11: 99000 | O11: 132000 | P11: 118000
A12: AR_PIPE | B12: Customer receipts, sales pipeline | C12: 1 | D12: 0 | E12: 60000 | F12: 0 | G12: 75000 | H12: 0 | I12: 0 | J12: 90000 | K12: 0 | L12: 55000 | M12: 0 | N12: 70000 | O12: 0 | P12: 80000
A13: VAT_REFUND | B13: VAT input refund | C13: 4 | D13: 0 | E13: 0 | F13: 0 | G13: 0 | H13: 0 | I13: 0 | J13: 0 | K13: 0 | L13: 148000 | M13: 0 | N13: 0 | O13: 0 | P13: 0
A14: AP_IMPORT | B14: Payment to import suppliers | C14: 5 | D14: 0 | E14: -430000 | F14: 0 | G14: 0 | H14: -415000 | I14: 0 | J14: 0 | K14: -470000 | L14: 0 | M14: 0 | N14: -402000 | O14: 0 | P14: 0
A15: AP_CUSTOMS | B15: Customs and freight clearance | C15: 5 | D15: 0 | E15: -86000 | F15: 0 | G15: 0 | H15: -83000 | I15: 0 | J15: 0 | K15: -94000 | L15: 0 | M15: 0 | N15: -79000 | O15: 0 | P15: 0
A16: AP_STOCK | B16: Year end season stock purchase | C16: 4 | D16: 0 | E16: 0 | F16: 0 | G16: 0 | H16: 0 | I16: 0 | J16: -225000 | K16: 0 | L16: 0 | M16: 0 | N16: 0 | O16: 0 | P16: 0
A17: PAYROLL | B17: Payroll and related | C17: 5 | D17: 0 | E17: 0 | F17: 0 | G17: -168000 | H17: 0 | I17: 0 | J17: 0 | K17: -171000 | L17: 0 | M17: 0 | N17: 0 | O17: -169000 | P17: 0
A18: TAX_102 | B18: Withholding, form 102 | C18: 5 | D18: 0 | E18: 0 | F18: 0 | G18: 0 | H18: -41000 | I18: 0 | J18: 0 | K18: 0 | L18: -42000 | M18: 0 | N18: 0 | O18: 0 | P18: -41500
A19: TAX_NI | B19: Social security | C19: 5 | D19: 0 | E19: 0 | F19: 0 | G19: 0 | H19: -23000 | I19: 0 | J19: 0 | K19: 0 | L19: -23500 | M19: 0 | N19: 0 | O19: 0 | P19: -23200
A20: TAX_VAT | B20: VAT, bimonthly payment | C20: 5 | D20: 0 | E20: 0 | F20: 0 | G20: 0 | H20: 0 | I20: -214000 | J20: 0 | K20: 0 | L20: 0 | M20: 0 | N20: 0 | O20: 0 | P20: -226000
A21: TAX_ADV | B21: Income tax advances | C21: 5 | D21: 0 | E21: 0 | F21: 0 | G21: 0 | H21: 0 | I21: -78000 | J21: 0 | K21: 0 | L21: 0 | M21: 0 | N21: 0 | O21: 0 | P21: -78000
... A27: OWNER_DRAW | B27: Owner drawings | C27: 2 | D27: 0 | E27: 0 | F27: 0 | G27: -35000 | H27: 0 | I27: 0 | J27: 0 | K27: -35000 | L27: 0 | M27: 0 | N27: 0 | O27: -35000 | P27: 0
A29: TOTAL_IN | B29: Total receipts, week | D29: =SUMPRODUCT((D$10:D$27>0)*D$10:D$27*IF($B$4="DOWN",($C$10:$C$27>=4)*1,1))*IF($B$4="UP",1.1,IF($B$4="DOWN",0.85,1)) | E29: =SUMPRODUCT((E$10:E$27>0)*E$10:E$27*IF($B$4="DOWN",($C$10:$C$27>=4)*1,1))*IF($B$4="UP",1.1,IF($B$4="DOWN",0.85,1)) | F29: =SUMPRODUCT((F$10:F$27>0)*F$10:F$27*IF($B$4="DOWN",($C$10:$C$27>=4)*1,1))*IF($B$4="UP",1.1,IF($B$4="DOWN",0.85,1)) | G29: =SUMPRODUCT((G$10:G$27>0)*G$10:G$27*IF($B$4="DOWN",($C$10:$C$27>=4)*1,1))*IF($B$4="UP",1.1,IF($B$4="DOWN",0.85,1)) | H29: =SUMPRODUCT((H$10:H$27>0)*H$10:H$27*IF($B$4="DOWN",($C$10:$C$27>=4)*1,1))*IF($B$4="UP",1.1,IF($B$4="DOWN",0.85,1)) | I29: =SUMPRODUCT((I$10:I$27>0)*I$10:I$27*IF($B$4="DOWN",($C$10:$C$27>=4)*1,1))*IF($B$4="UP",1.1,IF($B$4="DOWN",0.85,1)) | J29: =SUMPRODUCT((J$10:J$27>0)*J$10:J$27*IF($B$4="DOWN",($C$10:$C$27>=4)*1,1))*IF($B$4="UP",1.1,IF($B$4="DOWN",0.85,1)) | K29: =SUMPRODUCT((K$10:K$27>0)*K$10:K$27*IF($B$4="DOWN",($C$10:$C$27>=4)*1,1))*IF($B$4="UP",1.1,IF($B$4="DOWN",0.85,1)) | ... P29: =SUMPRODUCT((P$10:P$27>0)*P$10:P$27*IF($B$4="DOWN",($C$10:$C$27>=4)*1,1))*IF($B$4="UP",1.1,IF($B$4="DOWN",0.85,1)) | Q29: =SUM(D29:P29)
A30: TOTAL_OUT | B30: Total payments, week | D30: =SUMPRODUCT((D$10:D$27<0)*D$10:D$27) | E30: =SUMPRODUCT((E$10:E$27<0)*E$10:E$27) | F30: =SUMPRODUCT((F$10:F$27<0)*F$10:F$27) | G30: =SUMPRODUCT((G$10:G$27<0)*G$10:G$27) | H30: =SUMPRODUCT((H$10:H$27<0)*H$10:H$27) | I30: =SUMPRODUCT((I$10:I$27<0)*I$10:I$27) | J30: =SUMPRODUCT((J$10:J$27<0)*J$10:J$27) | K30: =SUMPRODUCT((K$10:K$27<0)*K$10:K$27) | ... P30: =SUMPRODUCT((P$10:P$27<0)*P$10:P$27) | Q30: =SUM(D30:P30)
A31: NET | B31: Net cash flow, week | D31: =D29+D30 | E31: =E29+E30 | F31: =F29+F30 | G31: =G29+G30 | H31: =H29+H30 | I31: =I29+I30 | J31: =J29+J30 | K31: =K29+K30 | ... P31: =P29+P30 | Q31: =SUM(D31:P31)
A32: OPEN | B32: Opening balance, week | D32: =IF(COLUMN()=4,$B$5,C33) | E32: =IF(COLUMN()=4,$B$5,D33) | F32: =IF(COLUMN()=4,$B$5,E33) | G32: =IF(COLUMN()=4,$B$5,F33) | H32: =IF(COLUMN()=4,$B$5,G33) | I32: =IF(COLUMN()=4,$B$5,H33) | J32: =IF(COLUMN()=4,$B$5,I33) | K32: =IF(COLUMN()=4,$B$5,J33) | ... P32: =IF(COLUMN()=4,$B$5,O33) | Q32: =D32
A33: CLOSE | B33: Closing balance, week | D33: =D32+D31 | E33: =E32+E31 | F33: =F32+F31 | G33: =G32+G31 | H33: =H32+H31 | I33: =I32+I31 | J33: =J32+J31 | K33: =K32+K31 | ... P33: =P32+P31 | Q33: =P33
A34: FACILITY_USE | B34: Facility used | D34: =MAX(0,-D33) | E34: =MAX(0,-E33) | F34: =MAX(0,-F33) | G34: =MAX(0,-G33) | H34: =MAX(0,-H33) | I34: =MAX(0,-I33) | J34: =MAX(0,-J33) | K34: =MAX(0,-K33) | ... P34: =MAX(0,-P33) | Q34: =MAX(D34:P34)
A35: STATUS | B35: Status | D35: =IF(D33>=0,"OK",IF(D34<=$B$6,"LINE","BREACH")) | E35: =IF(E33>=0,"OK",IF(E34<=$B$6,"LINE","BREACH")) | F35: =IF(F33>=0,"OK",IF(F34<=$B$6,"LINE","BREACH")) | G35: =IF(G33>=0,"OK",IF(G34<=$B$6,"LINE","BREACH")) | H35: =IF(H33>=0,"OK",IF(H34<=$B$6,"LINE","BREACH")) | I35: =IF(I33>=0,"OK",IF(I34<=$B$6,"LINE","BREACH")) | J35: =IF(J33>=0,"OK",IF(J34<=$B$6,"LINE","BREACH")) | K35: =IF(K33>=0,"OK",IF(K34<=$B$6,"LINE","BREACH")) | ... P35: =IF(P33>=0,"OK",IF(P34<=$B$6,"LINE","BREACH")) | Q35: =IF(COUNTIF(D35:P35,"BREACH")>0,"BREACH",IF(COUNTIF(D35:P35,"LINE")>0,"LINE","OK"))
A37: מקרא הקודים
A38: UP | B38: אופטימי, 110% מהתקבולים
A39: BASE | B39: בסיס, 100%
A40: DOWN | B40: פסימי: רק שורות בדירוג ודאות 4 ומעלה, ו-85% מהסכום
A41: OK | B41: יתרה חיובית
A42: LINE | B42: שימוש במסגרת האשראי
A43: BREACH | B43: חריגה מהמסגרת
A45: שימו לב שבשבוע 6 נופלים באותו שבוע גם מע"מ וגם מקדמות. זה לוח הזמנים החוקי ולא מקרה. תזרים שלא מכיל את לוח תשלומי המס אינו תזרים אלא משאלה.
A46: שורת משיכת הבעלים בדירוג ודאות 2 היא הידית הגמישה ביותר במודל. דחיית משיכה בחודשיים היא לרוב ההבדל בין חריגה לשימוש רגיל במסגרת, ובמקביל היא משנה את חשיפת סעיף 3(ט1).
A47: הגרף למטה מצייר את יתרת הסגירה השבועית. ברגע שתמלאו את השורות, השבוע שנשבר יקפוץ לעין לפני שתספיקו לקרוא מספר אחד.

Sheet 40_ROLLING
A1: Lab 6 · תחזית מתגלגלת 3+9 / 4+8
A2: תקציב שנקבע בדצמבר מתיישן אחרי רבעון. תחזית מתגלגלת מחליפה תקציב באקטואל ככל שהשנה מתקדמת.
A4: ClosedMonths (חודשי אקטואל שנסגרו): | D4: 6 | F4: שנו ל-3 בשביל 3+9, ל-4 בשביל 4+8, ל-6 בשביל חצי שנה.
A5: AdjFactor (מקדם תיקון ליתרת השנה): | D5: 1 | F5: 1.00 ממשיכים לפי התקציב. 0.95 מורידים חמישה אחוזים לחודשים שנותרו. זו ההחלטה הניהולית היחידה במודל.
A8: Row | B8: Jan | C8: Feb | D8: Mar | E8: Apr | F8: May | G8: Jun | H8: Jul | I8: Aug | J8: Sep | K8: Oct | L8: Nov | M8: Dec | N8: FY Total
A9: BUDGET_LOCKED · Original budget, locked | B9: =SUMIFS(BUDGET[Budget],BUDGET[Grp],"REVENUE",BUDGET[Month],COLUMN()-1) | C9: =SUMIFS(BUDGET[Budget],BUDGET[Grp],"REVENUE",BUDGET[Month],COLUMN()-1) | D9: =SUMIFS(BUDGET[Budget],BUDGET[Grp],"REVENUE",BUDGET[Month],COLUMN()-1) | E9: =SUMIFS(BUDGET[Budget],BUDGET[Grp],"REVENUE",BUDGET[Month],COLUMN()-1) | F9: =SUMIFS(BUDGET[Budget],BUDGET[Grp],"REVENUE",BUDGET[Month],COLUMN()-1) | G9: =SUMIFS(BUDGET[Budget],BUDGET[Grp],"REVENUE",BUDGET[Month],COLUMN()-1) | H9: =SUMIFS(BUDGET[Budget],BUDGET[Grp],"REVENUE",BUDGET[Month],COLUMN()-1) | I9: =SUMIFS(BUDGET[Budget],BUDGET[Grp],"REVENUE",BUDGET[Month],COLUMN()-1) | ... M9: =SUMIFS(BUDGET[Budget],BUDGET[Grp],"REVENUE",BUDGET[Month],COLUMN()-1) | N9: =SUM(B9:M9)
A10: ACTUAL · Actual | B10: =IF(COLUMN()-1<=$D$4,SUMIFS(GL[Amount],GL[Grp],"REVENUE",GL[Month],COLUMN()-1),"") | C10: =IF(COLUMN()-1<=$D$4,SUMIFS(GL[Amount],GL[Grp],"REVENUE",GL[Month],COLUMN()-1),"") | D10: =IF(COLUMN()-1<=$D$4,SUMIFS(GL[Amount],GL[Grp],"REVENUE",GL[Month],COLUMN()-1),"") | E10: =IF(COLUMN()-1<=$D$4,SUMIFS(GL[Amount],GL[Grp],"REVENUE",GL[Month],COLUMN()-1),"") | F10: =IF(COLUMN()-1<=$D$4,SUMIFS(GL[Amount],GL[Grp],"REVENUE",GL[Month],COLUMN()-1),"") | G10: =IF(COLUMN()-1<=$D$4,SUMIFS(GL[Amount],GL[Grp],"REVENUE",GL[Month],COLUMN()-1),"") | H10: =IF(COLUMN()-1<=$D$4,SUMIFS(GL[Amount],GL[Grp],"REVENUE",GL[Month],COLUMN()-1),"") | I10: =IF(COLUMN()-1<=$D$4,SUMIFS(GL[Amount],GL[Grp],"REVENUE",GL[Month],COLUMN()-1),"") | ... M10: =IF(COLUMN()-1<=$D$4,SUMIFS(GL[Amount],GL[Grp],"REVENUE",GL[Month],COLUMN()-1),"") | N10: =SUM(B10:M10)
A11: FORECAST · Rolling forecast | B11: =IF(COLUMN()-1<=$D$4,B10,B9*$D$5) | C11: =IF(COLUMN()-1<=$D$4,C10,C9*$D$5) | D11: =IF(COLUMN()-1<=$D$4,D10,D9*$D$5) | E11: =IF(COLUMN()-1<=$D$4,E10,E9*$D$5) | F11: =IF(COLUMN()-1<=$D$4,F10,F9*$D$5) | G11: =IF(COLUMN()-1<=$D$4,G10,G9*$D$5) | H11: =IF(COLUMN()-1<=$D$4,H10,H9*$D$5) | I11: =IF(COLUMN()-1<=$D$4,I10,I9*$D$5) | ... M11: =IF(COLUMN()-1<=$D$4,M10,M9*$D$5) | N11: =SUM(B11:M11)
A12: GAP · Forecast vs budget gap | B12: =B11-B9 | C12: =C11-C9 | D12: =D11-D9 | E12: =E11-E9 | F12: =F11-F9 | G12: =G11-G9 | H12: =H11-H9 | I12: =I11-I9 | ... N12: =N11-N9
A13: GAP_PCT · Gap percent | B13: =IFERROR(B12/B9,0) | C13: =IFERROR(C12/C9,0) | D13: =IFERROR(D12/D9,0) | E13: =IFERROR(E12/E9,0) | F13: =IFERROR(F12/F9,0) | G13: =IFERROR(G12/G9,0) | H13: =IFERROR(H12/H9,0) | I13: =IFERROR(I12/I9,0) | ... N13: =IFERROR(N12/N9,0)
A16: מה זה אומר לניהול
A17: תחזית שנתית מעודכנת | C17: =N11
A18: קו בסיס שנתי מקורי | C18: =N9
A19: פער שנתי צפוי | C19: =N11-N9
A20: האם צפויה עמידה ביעד | C20: =IF(N11>=N9,"ON_TRACK","ACTION_NEEDED")
A22: מקרא הקודים
A23: ON_TRACK | B23: התחזית עומדת בקו הבסיס
A24: ACTION_NEEDED | B24: התחזית מתחת לקו הבסיס, נדרשת פעולה
A26: ברגע שיש תחזית שנתית מעודכנת אפשר לחשב מקדמות נכונות ולהגיש בקשה להקטנת מקדמות לפי סעיף 175 אם התחזית נמוכה מהמחזור שעליו נקבע המקדם. זה הכסף הכי זול שמשרד רואה חשבון יכול לחסוך ללקוח, והוא זמין רק למי שיש לו תחזית.

Sheet 50_CREDIT_TERMS
A1: ארגז הכלים · כמה עולה לתת ללקוח תנאי תשלום ארוכים
A2: מגיע מוכן ועובד. לא נבנה בכיתה. שנו רק את התאים בקרם.
A3: לקוח שמבקש שוטף פלוס 90 במקום שוטף פלוס 30 לא מבקש הנחה, אבל הוא לוקח מכם כסף. הכלי מתרגם את הבקשה לשקלים, וגם אומר איזו הנחה כדאי להציע לו תמורת תשלום מיידי.
A5: הנתונים שאתם מזינים
A6: מחזור שנתי מהלקוח הזה | B6: 1800000
A7: תנאי התשלום היום, ימים | B7: 30
A8: תנאי התשלום המבוקשים, ימים | B8: 90
A9: ריבית האשראי הבנקאי שלכם, שנתי | B9: 0.08
A10: שיעור הרווח הגולמי על הלקוח הזה | B10: 0.35
A12: מה זה אומר
A13: מחזור יומי מהלקוח | B13: =B6/365
A14: כסף שתפוס אצלו היום | B14: =B13*B7
A15: כסף שיהיה תפוס אצלו בתנאים החדשים | B15: =B13*B8
A16: תוספת המימון שאתם נותנים לו | B16: =B15-B14
A17: כמה זה עולה לכם בשנה | B17: =B16*B9
A18: העלות כאחוז מהמחזור מהלקוח | B18: =B17/B6
A19: העלות ככרסום ברווח הגולמי מהלקוח | B19: =B17/(B6*B10)
A20: ההנחה המקסימלית ששווה לתת עבור תשלום מיידי | B20: =(B7/365)*B9
A21: ובשקלים, על המחזור מהלקוח | B21: =B20*B6
A23: שורה 16 היא הכסף שתעבירו ללקוח בלי לקרוא לזה הלוואה. שורה 17 היא כמה זה עולה לכם בשנה, בהנחה שהפער ממומן באשראי בנקאי.
A24: שורה 19 היא המספר שמשכנע: כמה אחוזים מהרווח הגולמי על הלקוח הזה נאכלים רק בגלל תנאי התשלום.
A25: שורה 20 היא הכלי המסחרי: אם ההנחה שהלקוח מבקש תמורת תשלום מיידי קטנה מהמספר הזה, כדאי לתת אותה. אם גדולה, עדיף לממן.
A26: הכלי מניח שהפער ממומן באשראי. אם יש לכם מזומן פנוי, השתמשו בתשואה החלופית שלכם במקום בריבית הבנקאית.

Sheet 60_CASH13_BLANK
A1: ארגז הכלים · תבנית תזרים 13 שבועות ריקה
A2: אותו מנוע של מעבדה 5, בלי נתונים. הנוסחאות כבר בפנים.
A3: הוראות: כתבו שמות שורות בעמודה B, דרגו ודאות 1 עד 5 בעמודה C, והזינו סכומים. תקבולים כמספר חיובי, תשלומים כמספר שלילי. שורות הסיכום מחשבות לבד.
A5: Scenario: | B5: BASE
A6: Opening: | B6: 0
A7: Facility: | B7: 0
A10: Line | B10: LineName | C10: Conf | D10: W1 | E10: W2 | F10: W3 | G10: W4 | H10: W5 | I10: W6 | J10: W7 | K10: W8 | L10: W9 | M10: W10 | N10: W11 | O10: W12 | P10: W13 | Q10: Total
A34: TOTAL_IN | B34: Total receipts, week | D34: =SUMPRODUCT((D$11:D$32>0)*D$11:D$32*IF($B$5="DOWN",($C$11:$C$32>=4)*1,1))*IF($B$5="UP",1.1,IF($B$5="DOWN",0.85,1)) | E34: =SUMPRODUCT((E$11:E$32>0)*E$11:E$32*IF($B$5="DOWN",($C$11:$C$32>=4)*1,1))*IF($B$5="UP",1.1,IF($B$5="DOWN",0.85,1)) | F34: =SUMPRODUCT((F$11:F$32>0)*F$11:F$32*IF($B$5="DOWN",($C$11:$C$32>=4)*1,1))*IF($B$5="UP",1.1,IF($B$5="DOWN",0.85,1)) | G34: =SUMPRODUCT((G$11:G$32>0)*G$11:G$32*IF($B$5="DOWN",($C$11:$C$32>=4)*1,1))*IF($B$5="UP",1.1,IF($B$5="DOWN",0.85,1)) | H34: =SUMPRODUCT((H$11:H$32>0)*H$11:H$32*IF($B$5="DOWN",($C$11:$C$32>=4)*1,1))*IF($B$5="UP",1.1,IF($B$5="DOWN",0.85,1)) | I34: =SUMPRODUCT((I$11:I$32>0)*I$11:I$32*IF($B$5="DOWN",($C$11:$C$32>=4)*1,1))*IF($B$5="UP",1.1,IF($B$5="DOWN",0.85,1)) | J34: =SUMPRODUCT((J$11:J$32>0)*J$11:J$32*IF($B$5="DOWN",($C$11:$C$32>=4)*1,1))*IF($B$5="UP",1.1,IF($B$5="DOWN",0.85,1)) | K34: =SUMPRODUCT((K$11:K$32>0)*K$11:K$32*IF($B$5="DOWN",($C$11:$C$32>=4)*1,1))*IF($B$5="UP",1.1,IF($B$5="DOWN",0.85,1)) | ... P34: =SUMPRODUCT((P$11:P$32>0)*P$11:P$32*IF($B$5="DOWN",($C$11:$C$32>=4)*1,1))*IF($B$5="UP",1.1,IF($B$5="DOWN",0.85,1)) | Q34: =SUM(D34:P34)
A35: TOTAL_OUT | B35: Total payments, week | D35: =SUMPRODUCT((D$11:D$32<0)*D$11:D$32) | E35: =SUMPRODUCT((E$11:E$32<0)*E$11:E$32) | F35: =SUMPRODUCT((F$11:F$32<0)*F$11:F$32) | G35: =SUMPRODUCT((G$11:G$32<0)*G$11:G$32) | H35: =SUMPRODUCT((H$11:H$32<0)*H$11:H$32) | I35: =SUMPRODUCT((I$11:I$32<0)*I$11:I$32) | J35: =SUMPRODUCT((J$11:J$32<0)*J$11:J$32) | K35: =SUMPRODUCT((K$11:K$32<0)*K$11:K$32) | ... P35: =SUMPRODUCT((P$11:P$32<0)*P$11:P$32) | Q35: =SUM(D35:P35)
A36: NET | B36: Net cash flow, week | D36: =D34+D35 | E36: =E34+E35 | F36: =F34+F35 | G36: =G34+G35 | H36: =H34+H35 | I36: =I34+I35 | J36: =J34+J35 | K36: =K34+K35 | ... P36: =P34+P35 | Q36: =SUM(D36:P36)
A37: OPEN | B37: Opening balance, week | D37: =IF(COLUMN()=4,$B$6,C38) | E37: =IF(COLUMN()=4,$B$6,D38) | F37: =IF(COLUMN()=4,$B$6,E38) | G37: =IF(COLUMN()=4,$B$6,F38) | H37: =IF(COLUMN()=4,$B$6,G38) | I37: =IF(COLUMN()=4,$B$6,H38) | J37: =IF(COLUMN()=4,$B$6,I38) | K37: =IF(COLUMN()=4,$B$6,J38) | ... P37: =IF(COLUMN()=4,$B$6,O38) | Q37: =D37
A38: CLOSE | B38: Closing balance, week | D38: =D37+D36 | E38: =E37+E36 | F38: =F37+F36 | G38: =G37+G36 | H38: =H37+H36 | I38: =I37+I36 | J38: =J37+J36 | K38: =K37+K36 | ... P38: =P37+P36 | Q38: =P38
A39: FACILITY_USE | B39: Facility used | D39: =MAX(0,-D38) | E39: =MAX(0,-E38) | F39: =MAX(0,-F38) | G39: =MAX(0,-G38) | H39: =MAX(0,-H38) | I39: =MAX(0,-I38) | J39: =MAX(0,-J38) | K39: =MAX(0,-K38) | ... P39: =MAX(0,-P38) | Q39: =MAX(D39:P39)
A40: STATUS | B40: Status | D40: =IF(D38>=0,"OK",IF(D39<=$B$7,"LINE","BREACH")) | E40: =IF(E38>=0,"OK",IF(E39<=$B$7,"LINE","BREACH")) | F40: =IF(F38>=0,"OK",IF(F39<=$B$7,"LINE","BREACH")) | G40: =IF(G38>=0,"OK",IF(G39<=$B$7,"LINE","BREACH")) | H40: =IF(H38>=0,"OK",IF(H39<=$B$7,"LINE","BREACH")) | I40: =IF(I38>=0,"OK",IF(I39<=$B$7,"LINE","BREACH")) | J40: =IF(J38>=0,"OK",IF(J39<=$B$7,"LINE","BREACH")) | K40: =IF(K38>=0,"OK",IF(K39<=$B$7,"LINE","BREACH")) | ... P40: =IF(P38>=0,"OK",IF(P39<=$B$7,"LINE","BREACH")) | Q40: =IF(COUNTIF(D40:P40,"BREACH")>0,"BREACH",IF(COUNTIF(D40:P40,"LINE")>0,"LINE","OK"))
A43: השורות בקרם ריקות ומחכות לכם. אם צריך יותר מ-22 שורות, הוסיפו שורות מעל השורה האחרונה כדי שהסיכומים יתרחבו איתן.

Sheet 99_KEY
A1: Formula Key · כל הנוסחאות
A2: כל נוסחה כאן היא ASCII בלבד. אפשר להעתיק ולהדביק אותה בכל מחשב בלי שהעברית תשבור אותה.
A4: Sheet | B4: Cell | C4: מה זה עושה | D4: Formula | E4: Fill
A5: 04_ETL | B5: E8 | C5: המרת תאריך טקסט לתאריך אמיתי, עמידה לשני פורמטים ובלתי תלויה בהגדרות אזור | D5: =LET(t,SUBSTITUTE(TRIM(A8),".","/"),d,VALUE(LEFT(t,FIND("/",t)-1)),r,MID(t,FIND("/",t)+1,20),m,VALUE(LEFT(r,FIND("/",r)-1)),y,VALUE(MID(r,FIND("/",r)+1,4)),DATE(IF(y<100,2000+y,y),m,d)) | E5: למטה
A6: 04_ETL | B6: F8 | C6: המרת סכום טקסט למספר. הסרת פסיקים ורווחים, וסוגריים כסימן לחיוב | D6: =LET(t,SUBSTITUTE(C8,UNICHAR(160)," "),n,SUBSTITUTE(SUBSTITUTE(TRIM(t)," ",""),",",""),IF(LEFT(n,1)="(",-VALUE(SUBSTITUTE(SUBSTITUTE(n,"(",""),")","")),VALUE(n))) | E6: למטה
A7: 04_ETL | B7: G8 | C7: ניקוי תיאור: תווים נסתרים שהבנק משאיר, ורווחים כפולים | D7: =TRIM(SUBSTITUTE(SUBSTITUTE(SUBSTITUTE(B8,UNICHAR(160)," "),UNICHAR(8207),""),UNICHAR(8206),"")) | E7: למטה
A8: 04_ETL | B8: H8 | C8: סיווג אוטומטי לפי טבלת המיפוי. מחזיר את קוד הסעיף של מילת המפתח הראשונה שנמצאה | D8: =IFERROR(INDEX(MAP[Acct],SUMPRODUCT(MATCH(1,--ISNUMBER(SEARCH(MAP[Keyword],G8)),0))),"UNMAPPED") | E8: למטה
A9: 04_ETL | B9: I8 | C9: זיהוי כפילות: אותה אסמכתא, אותו סכום ואותו תאריך מופיעים יותר מפעם אחת | D9: =IF(COUNTIFS($D$8:$D$108,D8,$F$8:$F$108,F8,$E$8:$E$108,E8)>1,"DUP","") | E9: למטה
A10: 04_ETL | B10: B112 | C10: שורות שנקלטו | D10: =COUNTA(D8:D108) | E10: תא בודד
A11: 04_ETL | B11: B113 | C11: שורות שלא סווגו | D11: =COUNTIF(H8:H108,"UNMAPPED") | E11: תא בודד
A12: 04_ETL | B12: B114 | C12: שורות שסומנו ככפילות | D12: =COUNTIF(I8:I108,"DUP") | E12: תא בודד
A13: 04_ETL | B13: B115 | C13: סה"כ תקבולים בקובץ, ללא כפילויות | D13: =SUMIFS(F8:F108,I8:I108,"",F8:F108,">0") | E13: תא בודד
A14: 04_ETL | B14: B116 | C14: סה"כ תשלומים בקובץ, ללא כפילויות | D14: =SUMIFS(F8:F108,I8:I108,"",F8:F108,"<0") | E14: תא בודד
A15: 04_ETL | B15: B117 | C15: סה"כ תשלומי מס בתקופה | D15: =SUMIFS(F8:F108,H8:H108,"TAX",I8:I108,"") | E15: תא בודד
... A81: 40_ROLLING | B81: C20 | C81: האם צפויה עמידה ביעד | D81: =IF(N11>=N9,"ON_TRACK","ACTION_NEEDED") | E81: תא בודד
